tshockapi/__init__.py
tshockapi-0.1.2.dist-info/WHEEL
tshockapi-0.1.2.dist-info/METADATA
tshockapi-0.1.2.dist-info/RECORD
