Metadata-Version: 2.1
Name: tshockapi
Version: 0.1.2
Summary: Quick access to TShock REST API using python.
Author: Qianyiovo
Author-email: qianyiovo@outlook.com
Requires-Python: >=3.7,<4.0
Classifier: Programming Language :: Python :: 3
Classifier: Programming Language :: Python :: 3.7
Classifier: Programming Language :: Python :: 3.8
Classifier: Programming Language :: Python :: 3.9
Classifier: Programming Language :: Python :: 3.10
Requires-Dist: httpx (>=0.23.0,<0.24.0)
